meteoplots/__init__.py
meteoplots/plots.py
meteoplots/colorbar/__init__.py
meteoplots/colorbar/colorbars.py
meteoplots/utils/__init__.py
meteoplots/utils/titles.py
meteoplots/utils/utils.py
meteoplots-0.1.4.dist-info/METADATA
meteoplots-0.1.4.dist-info/WHEEL
meteoplots-0.1.4.dist-info/top_level.txt
meteoplots-0.1.4.dist-info/RECORD
